asapi/__init__.py
asapi/_injected.py
asapi/_parameters.py
asapi/_serve.py
asapi/_signal_handling.py
asapi/py.typed
asapi-0.7.0.dist-info/METADATA
asapi-0.7.0.dist-info/WHEEL
asapi-0.7.0.dist-info/RECORD
