Metadata-Version: 2.4
Name: asapi
Version: 0.7.0
Summary: Thin wrapper around FastAPI
Author-email: Adrian Garcia Badaracco <1755071+adriangb@users.noreply.github.com>
Requires-Python: ~=3.9
Requires-Dist: anyio>=4.3.0
Requires-Dist: fastapi>=0.111.0
Requires-Dist: typing-extensions>=4.12.0
Requires-Dist: uvicorn>=0.30.0
